[
{ "seq_id" : 128, "qsl_idx" : 59, "data" : "4C020000" },
{ "seq_id" : 129, "qsl_idx" : 14812, "data" : "4C010000" },
{ "seq_id" : 130, "qsl_idx" : 14141, "data" : "11020000" },
{ "seq_id" : 131, "qsl_idx" : 24435, "data" : "09020000" },
{ "seq_id" : 132, "qsl_idx" : 23065, "data" : "53010000" },
{ "seq_id" : 133, "qsl_idx" : 2615, "data" : "B5000000" },
{ "seq_id" : 134, "qsl_idx" : 17420, "data" : "EE000000" },
{ "seq_id" : 135, "qsl_idx" : 34861, "data" : "CD030000" },
{ "seq_id" : 136, "qsl_idx" : 49069, "data" : "0B020000" },
{ "seq_id" : 137, "qsl_idx" : 37197, "data" : "36010000" },
{ "seq_id" : 138, "qsl_idx" : 45783, "data" : "82000000" },
{ "seq_id" : 139, "qsl_idx" : 21256, "data" : "3A030000" },
{ "seq_id" : 140, "qsl_idx" : 30949, "data" : "CA020000" },
{ "seq_id" : 141, "qsl_idx" : 21180, "data" : "63010000" },
{ "seq_id" : 142, "qsl_idx" : 14545, "data" : "A9030000" },
{ "seq_id" : 143, "qsl_idx" : 37441, "data" : "F6000000" },
{ "seq_id" : 144, "qsl_idx" : 31114, "data" : "68000000" },
{ "seq_id" : 145, "qsl_idx" : 38611, "data" : "2C030000" },
{ "seq_id" : 146, "qsl_idx" : 41830, "data" : "13010000" },
{ "seq_id" : 147, "qsl_idx" : 24281, "data" : "AA010000" },
{ "seq_id" : 148, "qsl_idx" : 1046, "data" : "9F000000" },
{ "seq_id" : 149, "qsl_idx" : 39960, "data" : "BF010000" },
{ "seq_id" : 150, "qsl_idx" : 15478, "data" : "F4010000" },
{ "seq_id" : 151, "qsl_idx" : 41911, "data" : "AF000000" },
{ "seq_id" : 152, "qsl_idx" : 47006, "data" : "FA020000" },
{ "seq_id" : 153, "qsl_idx" : 13211, "data" : "5B000000" },
{ "seq_id" : 154, "qsl_idx" : 38280, "data" : "84020000" },
{ "seq_id" : 155, "qsl_idx" : 28269, "data" : "38010000" },
{ "seq_id" : 156, "qsl_idx" : 49180, "data" : "07000000" },
{ "seq_id" : 157, "qsl_idx" : 13463, "data" : "67030000" },
{ "seq_id" : 158, "qsl_idx" : 13862, "data" : "59000000" },
{ "seq_id" : 159, "qsl_idx" : 15941, "data" : "DC030000" },
{ "seq_id" : 160, "qsl_idx" : 21871, "data" : "80000000" },
{ "seq_id" : 161, "qsl_idx" : 36776, "data" : "A2010000" },
{ "seq_id" : 162, "qsl_idx" : 41427, "data" : "B9020000" },
{ "seq_id" : 163, "qsl_idx" : 22422, "data" : "E2020000" },
{ "seq_id" : 164, "qsl_idx" : 16260, "data" : "A6010000" },
{ "seq_id" : 165, "qsl_idx" : 47826, "data" : "12000000" },
{ "seq_id" : 166, "qsl_idx" : 17827, "data" : "29020000" },
{ "seq_id" : 167, "qsl_idx" : 8978, "data" : "DF000000" },
{ "seq_id" : 168, "qsl_idx" : 17830, "data" : "83010000" },
{ "seq_id" : 169, "qsl_idx" : 39597, "data" : "AD020000" },
{ "seq_id" : 170, "qsl_idx" : 6948, "data" : "49020000" },
{ "seq_id" : 171, "qsl_idx" : 30142, "data" : "E1020000" },
{ "seq_id" : 172, "qsl_idx" : 6638, "data" : "48030000" },
{ "seq_id" : 173, "qsl_idx" : 10367, "data" : "11020000" },
{ "seq_id" : 174, "qsl_idx" : 29299, "data" : "03000000" },
{ "seq_id" : 175, "qsl_idx" : 22493, "data" : "56020000" },
{ "seq_id" : 176, "qsl_idx" : 9283, "data" : "3B030000" },
{ "seq_id" : 177, "qsl_idx" : 31702, "data" : "8B010000" },
{ "seq_id" : 178, "qsl_idx" : 23754, "data" : "17010000" },
{ "seq_id" : 179, "qsl_idx" : 25847, "data" : "5F030000" },
{ "seq_id" : 180, "qsl_idx" : 42148, "data" : "C8020000" },
{ "seq_id" : 181, "qsl_idx" : 31104, "data" : "6F000000" },
{ "seq_id" : 182, "qsl_idx" : 44921, "data" : "39000000" },
{ "seq_id" : 183, "qsl_idx" : 35699, "data" : "93000000" },
{ "seq_id" : 184, "qsl_idx" : 40131, "data" : "2F010000" },
{ "seq_id" : 185, "qsl_idx" : 21068, "data" : "2E000000" },
{ "seq_id" : 186, "qsl_idx" : 25887, "data" : "0B000000" },
{ "seq_id" : 187, "qsl_idx" : 33411, "data" : "1D000000" },
{ "seq_id" : 188, "qsl_idx" : 35542, "data" : "6F010000" },
{ "seq_id" : 189, "qsl_idx" : 33916, "data" : "96020000" },
{ "seq_id" : 190, "qsl_idx" : 44659, "data" : "85010000" },
{ "seq_id" : 191, "qsl_idx" : 3728, "data" : "DB000000" },
{ "seq_id" : 192, "qsl_idx" : 31657, "data" : "0D020000" },
{ "seq_id" : 193, "qsl_idx" : 27509, "data" : "6A010000" },
{ "seq_id" : 194, "qsl_idx" : 28997, "data" : "72030000" },
{ "seq_id" : 195, "qsl_idx" : 1035, "data" : "68000000" },
{ "seq_id" : 196, "qsl_id

...

: "12000000" },
{ "seq_id" : 49470, "qsl_idx" : 9215, "data" : "49000000" },
{ "seq_id" : 49471, "qsl_idx" : 11101, "data" : "2B020000" },
{ "seq_id" : 49920, "qsl_idx" : 35671, "data" : "94030000" },
{ "seq_id" : 49921, "qsl_idx" : 27060, "data" : "C7030000" },
{ "seq_id" : 49922, "qsl_idx" : 41039, "data" : "46020000" },
{ "seq_id" : 49923, "qsl_idx" : 2967, "data" : "B8010000" },
{ "seq_id" : 49924, "qsl_idx" : 27497, "data" : "0E000000" },
{ "seq_id" : 49925, "qsl_idx" : 29388, "data" : "76020000" },
{ "seq_id" : 49926, "qsl_idx" : 24313, "data" : "36000000" },
{ "seq_id" : 49927, "qsl_idx" : 11987, "data" : "42020000" },
{ "seq_id" : 49928, "qsl_idx" : 46387, "data" : "18010000" },
{ "seq_id" : 49929, "qsl_idx" : 40335, "data" : "1C030000" },
{ "seq_id" : 49930, "qsl_idx" : 9206, "data" : "0C020000" },
{ "seq_id" : 49931, "qsl_idx" : 21536, "data" : "5C020000" },
{ "seq_id" : 49932, "qsl_idx" : 27070, "data" : "98010000" },
{ "seq_id" : 49933, "qsl_idx" : 38224, "data" : "7A030000" },
{ "seq_id" : 49934, "qsl_idx" : 3943, "data" : "50030000" },
{ "seq_id" : 49935, "qsl_idx" : 48231, "data" : "36030000" },
{ "seq_id" : 49936, "qsl_idx" : 22239, "data" : "ED000000" },
{ "seq_id" : 49937, "qsl_idx" : 26945, "data" : "EB010000" },
{ "seq_id" : 49938, "qsl_idx" : 39655, "data" : "0B030000" },
{ "seq_id" : 49939, "qsl_idx" : 49792, "data" : "3C020000" },
{ "seq_id" : 49940, "qsl_idx" : 26847, "data" : "4D000000" },
{ "seq_id" : 49941, "qsl_idx" : 22485, "data" : "3C000000" },
{ "seq_id" : 49942, "qsl_idx" : 17930, "data" : "64000000" },
{ "seq_id" : 49943, "qsl_idx" : 2905, "data" : "45010000" },
{ "seq_id" : 49944, "qsl_idx" : 38905, "data" : "6D020000" },
{ "seq_id" : 49945, "qsl_idx" : 35039, "data" : "47010000" },
{ "seq_id" : 49946, "qsl_idx" : 42685, "data" : "FC010000" },
{ "seq_id" : 49947, "qsl_idx" : 24089, "data" : "A1000000" },
{ "seq_id" : 49948, "qsl_idx" : 7150, "data" : "77010000" },
{ "seq_id" : 49949, "qsl_idx" : 4231, "data" : "14030000" },
{ "seq_id" : 49950, "qsl_idx" : 30087, "data" : "AE000000" },
{ "seq_id" : 49951, "qsl_idx" : 39720, "data" : "84030000" },
{ "seq_id" : 49952, "qsl_idx" : 22132, "data" : "F9000000" },
{ "seq_id" : 49953, "qsl_idx" : 3843, "data" : "E1010000" },
{ "seq_id" : 49954, "qsl_idx" : 10507, "data" : "67020000" },
{ "seq_id" : 49955, "qsl_idx" : 44026, "data" : "1A010000" },
{ "seq_id" : 49956, "qsl_idx" : 43813, "data" : "3C030000" },
{ "seq_id" : 49957, "qsl_idx" : 28311, "data" : "C0020000" },
{ "seq_id" : 49958, "qsl_idx" : 30363, "data" : "FD000000" },
{ "seq_id" : 49959, "qsl_idx" : 11947, "data" : "99030000" },
{ "seq_id" : 49960, "qsl_idx" : 7328, "data" : "6D000000" },
{ "seq_id" : 49961, "qsl_idx" : 4564, "data" : "0F030000" },
{ "seq_id" : 49962, "qsl_idx" : 20216, "data" : "78010000" },
{ "seq_id" : 49963, "qsl_idx" : 2786, "data" : "46010000" },
{ "seq_id" : 49964, "qsl_idx" : 48720, "data" : "4C030000" },
{ "seq_id" : 49965, "qsl_idx" : 27234, "data" : "81030000" },
{ "seq_id" : 49966, "qsl_idx" : 27570, "data" : "B1030000" },
{ "seq_id" : 49967, "qsl_idx" : 21696, "data" : "BA000000" },
{ "seq_id" : 49968, "qsl_idx" : 27535, "data" : "42020000" },
{ "seq_id" : 49969, "qsl_idx" : 38673, "data" : "E0000000" },
{ "seq_id" : 49970, "qsl_idx" : 3113, "data" : "59020000" },
{ "seq_id" : 49971, "qsl_idx" : 34828, "data" : "30020000" },
{ "seq_id" : 49972, "qsl_idx" : 26021, "data" : "40000000" },
{ "seq_id" : 49973, "qsl_idx" : 28872, "data" : "A3030000" },
{ "seq_id" : 49974, "qsl_idx" : 13756, "data" : "20020000" },
{ "seq_id" : 49975, "qsl_idx" : 21755, "data" : "B0000000" },
{ "seq_id" : 49976, "qsl_idx" : 26095, "data" : "C1010000" },
{ "seq_id" : 49977, "qsl_idx" : 7515, "data" : "B1000000" },
{ "seq_id" : 49978, "qsl_idx" : 44499, "data" : "B2020000" },
{ "seq_id" : 49979, "qsl_idx" : 33488, "data" : "BE000000" },
{ "seq_id" : 49980, "qsl_idx" : 26498, "data" : "6D010000" },
{ "seq_id" : 49981, "qsl_idx" : 36871, "data" : "D8020000" },
{ "seq_id" : 49982, "qsl_idx" : 20409, "data" : "BE010000" },
{ "seq_id" : 49983, "qsl_idx" : 10475, "data" : "4F010000" }
]
