[
{ "seq_id" : 10, "qsl_idx" : 8798, "data" : "9903000000000000" },
{ "seq_id" : 9, "qsl_idx" : 2134, "data" : "3F02000000000000" },
{ "seq_id" : 3, "qsl_idx" : 15855, "data" : "C702000000000000" },
{ "seq_id" : 11, "qsl_idx" : 44491, "data" : "7003000000000000" },
{ "seq_id" : 7, "qsl_idx" : 39036, "data" : "DC01000000000000" },
{ "seq_id" : 2, "qsl_idx" : 14670, "data" : "1F02000000000000" },
{ "seq_id" : 0, "qsl_idx" : 37520, "data" : "E103000000000000" },
{ "seq_id" : 8, "qsl_idx" : 44591, "data" : "2302000000000000" },
{ "seq_id" : 1, "qsl_idx" : 21257, "data" : "0202000000000000" },
{ "seq_id" : 6, "qsl_idx" : 36293, "data" : "F101000000000000" },
{ "seq_id" : 5, "qsl_idx" : 8364, "data" : "F901000000000000" },
{ "seq_id" : 14, "qsl_idx" : 10688, "data" : "0A00000000000000" },
{ "seq_id" : 4, "qsl_idx" : 7562, "data" : "BB03000000000000" },
{ "seq_id" : 12, "qsl_idx" : 27134, "data" : "3802000000000000" },
{ "seq_id" : 15, "qsl_idx" : 32791, "data" : "9E03000000000000" },
{ "seq_id" : 18, "qsl_idx" : 43144, "data" : "1C01000000000000" },
{ "seq_id" : 16, "qsl_idx" : 12731, "data" : "2300000000000000" },
{ "seq_id" : 13, "qsl_idx" : 82, "data" : "1403000000000000" },
{ "seq_id" : 19, "qsl_idx" : 48322, "data" : "E901000000000000" },
{ "seq_id" : 26, "qsl_idx" : 28712, "data" : "0100000000000000" },
{ "seq_id" : 23, "qsl_idx" : 31866, "data" : "2F02000000000000" },
{ "seq_id" : 17, "qsl_idx" : 2512, "data" : "7F02000000000000" },
{ "seq_id" : 25, "qsl_idx" : 13052, "data" : "EC00000000000000" },
{ "seq_id" : 29, "qsl_idx" : 37768, "data" : "C602000000000000" },
{ "seq_id" : 27, "qsl_idx" : 9795, "data" : "E002000000000000" },
{ "seq_id" : 28, "qsl_idx" : 34686, "data" : "AB03000000000000" },
{ "seq_id" : 30, "qsl_idx" : 20350, "data" : "CA02000000000000" },
{ "seq_id" : 20, "qsl_idx" : 34046, "data" : "F001000000000000" },
{ "seq_id" : 22, "qsl_idx" : 21999, "data" : "4B01000000000000" },
{ "seq_id" : 21, "qsl_idx" : 35775, "data" : "7E02000000000000" },
{ "seq_id" : 31, "qsl_idx" : 9765, "data" : "E503000000000000" },
{ "seq_id" : 24, "qsl_idx" : 25218, "data" : "FF00000000000000" },
{ "seq_id" : 34, "qsl_idx" : 17636, "data" : "E801000000000000" },
{ "seq_id" : 32, "qsl_idx" : 19518, "data" : "F900000000000000" },
{ "seq_id" : 35, "qsl_idx" : 45921, "data" : "CE01000000000000" },
{ "seq_id" : 36, "qsl_idx" : 25518, "data" : "1C01000000000000" },
{ "seq_id" : 37, "qsl_idx" : 16334, "data" : "D700000000000000" },
{ "seq_id" : 38, "qsl_idx" : 15687, "data" : "EF02000000000000" },
{ "seq_id" : 46, "qsl_idx" : 1949, "data" : "2700000000000000" },
{ "seq_id" : 42, "qsl_idx" : 25795, "data" : "4200000000000000" },
{ "seq_id" : 33, "qsl_idx" : 37643, "data" : "D602000000000000" },
{ "seq_id" : 44, "qsl_idx" : 8561, "data" : "6A01000000000000" },
{ "seq_id" : 45, "qsl_idx" : 41465, "data" : "5C03000000000000" },
{ "seq_id" : 39, "qsl_idx" : 29817, "data" : "3601000000000000" },
{ "seq_id" : 47, "qsl_idx" : 29164, "data" : "8C03000000000000" },
{ "seq_id" : 41, "qsl_idx" : 31978, "data" : "C302000000000000" },
{ "seq_id" : 40, "qsl_idx" : 17650, "data" : "8E02000000000000" },
{ "seq_id" : 48, "qsl_idx" : 39069, "data" : "AA01000000000000" },
{ "seq_id" : 49, "qsl_idx" : 32470, "data" : "4700000000000000" },
{ "seq_id" : 43, "qsl_idx" : 1773, "data" : "8F01000000000000" },
{ "seq_id" : 51, "qsl_idx" : 31748, "data" : "3D00000000000000" },
{ "seq_id" : 50, "qsl_idx" : 46987, "data" : "9400000000000000" },
{ "seq_id" : 52, "qsl_idx" : 14772, "data" : "1C01000000000000" },
{ "seq_id" : 53, "qsl_idx" : 1137, "data" : "1D00000000000000" },
{ "seq_id" : 54, "qsl_idx" : 39279, "data" : "C803000000000000" },
{ "seq_id" : 55, "qsl_idx" : 5323, "data" : "8B02000000000000" },
{ "seq_id" : 57, "qsl_idx" : 4625, "data" : "CF03000000000000" },
{ "seq_id" : 61, "qsl_idx" : 10336, "data" : "4002000000000000" },
{ "seq_id" : 60, "qsl_idx" : 47405, "data" : "6700000000000000" },
{ "seq_id" : 58, "qsl_idx" : 9282, "data" : "7801000000000000" },
{ "seq_id" : 59, "qsl_idx" : 22629, "data" : "9A00000000000000" },
{ "seq_id" : 62, "qsl_idx" : 22760

...

l_idx" : 2905, "data" : "4501000000000000" },
{ "seq_id" : 49941, "qsl_idx" : 22485, "data" : "3C00000000000000" },
{ "seq_id" : 49944, "qsl_idx" : 38905, "data" : "6D02000000000000" },
{ "seq_id" : 49946, "qsl_idx" : 42685, "data" : "FC01000000000000" },
{ "seq_id" : 49942, "qsl_idx" : 17930, "data" : "6400000000000000" },
{ "seq_id" : 49948, "qsl_idx" : 7150, "data" : "7701000000000000" },
{ "seq_id" : 49945, "qsl_idx" : 35039, "data" : "4701000000000000" },
{ "seq_id" : 49947, "qsl_idx" : 24089, "data" : "A100000000000000" },
{ "seq_id" : 49949, "qsl_idx" : 4231, "data" : "1403000000000000" },
{ "seq_id" : 49950, "qsl_idx" : 30087, "data" : "AE00000000000000" },
{ "seq_id" : 49951, "qsl_idx" : 39720, "data" : "8403000000000000" },
{ "seq_id" : 49952, "qsl_idx" : 22132, "data" : "F900000000000000" },
{ "seq_id" : 49955, "qsl_idx" : 44026, "data" : "1A01000000000000" },
{ "seq_id" : 49956, "qsl_idx" : 43813, "data" : "3C03000000000000" },
{ "seq_id" : 49953, "qsl_idx" : 3843, "data" : "E101000000000000" },
{ "seq_id" : 49957, "qsl_idx" : 28311, "data" : "C002000000000000" },
{ "seq_id" : 49958, "qsl_idx" : 30363, "data" : "FD00000000000000" },
{ "seq_id" : 49954, "qsl_idx" : 10507, "data" : "6702000000000000" },
{ "seq_id" : 49960, "qsl_idx" : 7328, "data" : "6D00000000000000" },
{ "seq_id" : 49959, "qsl_idx" : 11947, "data" : "9903000000000000" },
{ "seq_id" : 49963, "qsl_idx" : 2786, "data" : "4601000000000000" },
{ "seq_id" : 49961, "qsl_idx" : 4564, "data" : "0F03000000000000" },
{ "seq_id" : 49962, "qsl_idx" : 20216, "data" : "7801000000000000" },
{ "seq_id" : 49965, "qsl_idx" : 27234, "data" : "8103000000000000" },
{ "seq_id" : 49966, "qsl_idx" : 27570, "data" : "B103000000000000" },
{ "seq_id" : 49964, "qsl_idx" : 48720, "data" : "4C03000000000000" },
{ "seq_id" : 49969, "qsl_idx" : 38673, "data" : "E000000000000000" },
{ "seq_id" : 49967, "qsl_idx" : 21696, "data" : "BA00000000000000" },
{ "seq_id" : 49968, "qsl_idx" : 27535, "data" : "4202000000000000" },
{ "seq_id" : 49970, "qsl_idx" : 3113, "data" : "5902000000000000" },
{ "seq_id" : 49975, "qsl_idx" : 21755, "data" : "B000000000000000" },
{ "seq_id" : 49971, "qsl_idx" : 34828, "data" : "3002000000000000" },
{ "seq_id" : 49972, "qsl_idx" : 26021, "data" : "4000000000000000" },
{ "seq_id" : 49973, "qsl_idx" : 28872, "data" : "A303000000000000" },
{ "seq_id" : 49976, "qsl_idx" : 26095, "data" : "C101000000000000" },
{ "seq_id" : 49977, "qsl_idx" : 7515, "data" : "B100000000000000" },
{ "seq_id" : 49974, "qsl_idx" : 13756, "data" : "2002000000000000" },
{ "seq_id" : 49979, "qsl_idx" : 33488, "data" : "BE00000000000000" },
{ "seq_id" : 49978, "qsl_idx" : 44499, "data" : "B202000000000000" },
{ "seq_id" : 49983, "qsl_idx" : 10475, "data" : "4F01000000000000" },
{ "seq_id" : 49980, "qsl_idx" : 26498, "data" : "6D01000000000000" },
{ "seq_id" : 49986, "qsl_idx" : 48038, "data" : "6400000000000000" },
{ "seq_id" : 49981, "qsl_idx" : 36871, "data" : "FE02000000000000" },
{ "seq_id" : 49987, "qsl_idx" : 38258, "data" : "3D03000000000000" },
{ "seq_id" : 49989, "qsl_idx" : 29328, "data" : "8700000000000000" },
{ "seq_id" : 49982, "qsl_idx" : 20409, "data" : "BE01000000000000" },
{ "seq_id" : 49985, "qsl_idx" : 47447, "data" : "B003000000000000" },
{ "seq_id" : 49984, "qsl_idx" : 26815, "data" : "A702000000000000" },
{ "seq_id" : 49990, "qsl_idx" : 346, "data" : "D801000000000000" },
{ "seq_id" : 49988, "qsl_idx" : 23669, "data" : "5503000000000000" },
{ "seq_id" : 49991, "qsl_idx" : 19541, "data" : "8803000000000000" },
{ "seq_id" : 49993, "qsl_idx" : 20929, "data" : "A100000000000000" },
{ "seq_id" : 49998, "qsl_idx" : 39228, "data" : "E102000000000000" },
{ "seq_id" : 49992, "qsl_idx" : 14730, "data" : "8500000000000000" },
{ "seq_id" : 49994, "qsl_idx" : 21136, "data" : "7501000000000000" },
{ "seq_id" : 49995, "qsl_idx" : 12560, "data" : "6503000000000000" },
{ "seq_id" : 49997, "qsl_idx" : 19250, "data" : "5F00000000000000" },
{ "seq_id" : 49996, "qsl_idx" : 44463, "data" : "E500000000000000" },
{ "seq_id" : 49999, "qsl_idx" : 5950, "data" : "5A01000000000000" }
]
