[
{ "seq_id" : 1280, "qsl_idx" : 3725, "data" : "D0000000" },
{ "seq_id" : 1281, "qsl_idx" : 17682, "data" : "89010000" },
{ "seq_id" : 1282, "qsl_idx" : 2621, "data" : "37000000" },
{ "seq_id" : 1283, "qsl_idx" : 1046, "data" : "9F000000" },
{ "seq_id" : 1284, "qsl_idx" : 12401, "data" : "85000000" },
{ "seq_id" : 1285, "qsl_idx" : 16177, "data" : "4E030000" },
{ "seq_id" : 1286, "qsl_idx" : 16875, "data" : "29020000" },
{ "seq_id" : 1287, "qsl_idx" : 45715, "data" : "EE010000" },
{ "seq_id" : 1288, "qsl_idx" : 43452, "data" : "2F020000" },
{ "seq_id" : 1289, "qsl_idx" : 47049, "data" : "BD010000" },
{ "seq_id" : 1290, "qsl_idx" : 40126, "data" : "3B030000" },
{ "seq_id" : 1291, "qsl_idx" : 35441, "data" : "87030000" },
{ "seq_id" : 1292, "qsl_idx" : 36992, "data" : "C9020000" },
{ "seq_id" : 1293, "qsl_idx" : 26798, "data" : "9B020000" },
{ "seq_id" : 1294, "qsl_idx" : 29084, "data" : "13030000" },
{ "seq_id" : 1295, "qsl_idx" : 9580, "data" : "76010000" },
{ "seq_id" : 1296, "qsl_idx" : 38326, "data" : "E4030000" },
{ "seq_id" : 1297, "qsl_idx" : 41685, "data" : "99030000" },
{ "seq_id" : 1298, "qsl_idx" : 34258, "data" : "C8000000" },
{ "seq_id" : 1299, "qsl_idx" : 31421, "data" : "00000000" },
{ "seq_id" : 1300, "qsl_idx" : 46000, "data" : "CE020000" },
{ "seq_id" : 1301, "qsl_idx" : 20907, "data" : "4E030000" },
{ "seq_id" : 1302, "qsl_idx" : 7271, "data" : "EF010000" },
{ "seq_id" : 1303, "qsl_idx" : 831, "data" : "F8020000" },
{ "seq_id" : 1304, "qsl_idx" : 40174, "data" : "F9020000" },
{ "seq_id" : 1305, "qsl_idx" : 37824, "data" : "91000000" },
{ "seq_id" : 1306, "qsl_idx" : 6682, "data" : "F3020000" },
{ "seq_id" : 1307, "qsl_idx" : 19308, "data" : "CC020000" },
{ "seq_id" : 1308, "qsl_idx" : 34514, "data" : "51000000" },
{ "seq_id" : 1309, "qsl_idx" : 34509, "data" : "5B000000" },
{ "seq_id" : 1310, "qsl_idx" : 5388, "data" : "B2010000" },
{ "seq_id" : 1311, "qsl_idx" : 47006, "data" : "FA020000" },
{ "seq_id" : 1312, "qsl_idx" : 32095, "data" : "9B010000" },
{ "seq_id" : 1313, "qsl_idx" : 21836, "data" : "24030000" },
{ "seq_id" : 1314, "qsl_idx" : 42155, "data" : "88000000" },
{ "seq_id" : 1315, "qsl_idx" : 25601, "data" : "D7020000" },
{ "seq_id" : 1316, "qsl_idx" : 8630, "data" : "16010000" },
{ "seq_id" : 1317, "qsl_idx" : 29146, "data" : "4C000000" },
{ "seq_id" : 1318, "qsl_idx" : 35200, "data" : "A3030000" },
{ "seq_id" : 1319, "qsl_idx" : 46407, "data" : "86000000" },
{ "seq_id" : 1320, "qsl_idx" : 4052, "data" : "B6000000" },
{ "seq_id" : 1321, "qsl_idx" : 8767, "data" : "BF020000" },
{ "seq_id" : 1322, "qsl_idx" : 16247, "data" : "E1020000" },
{ "seq_id" : 1323, "qsl_idx" : 23536, "data" : "91020000" },
{ "seq_id" : 1324, "qsl_idx" : 35487, "data" : "A8000000" },
{ "seq_id" : 1325, "qsl_idx" : 28401, "data" : "F9000000" },
{ "seq_id" : 1326, "qsl_idx" : 28710, "data" : "0B030000" },
{ "seq_id" : 1327, "qsl_idx" : 7127, "data" : "82000000" },
{ "seq_id" : 1328, "qsl_idx" : 21841, "data" : "11030000" },
{ "seq_id" : 1329, "qsl_idx" : 38351, "data" : "65030000" },
{ "seq_id" : 1330, "qsl_idx" : 43286, "data" : "8C020000" },
{ "seq_id" : 1331, "qsl_idx" : 5384, "data" : "69030000" },
{ "seq_id" : 1332, "qsl_idx" : 45061, "data" : "11000000" },
{ "seq_id" : 1333, "qsl_idx" : 23149, "data" : "4C030000" },
{ "seq_id" : 1334, "qsl_idx" : 2324, "data" : "AB000000" },
{ "seq_id" : 1335, "qsl_idx" : 19518, "data" : "F9000000" },
{ "seq_id" : 1336, "qsl_idx" : 40427, "data" : "D7010000" },
{ "seq_id" : 1337, "qsl_idx" : 9046, "data" : "8F000000" },
{ "seq_id" : 1338, "qsl_idx" : 4290, "data" : "BA010000" },
{ "seq_id" : 1339, "qsl_idx" : 37441, "data" : "F6000000" },
{ "seq_id" : 1340, "qsl_idx" : 31033, "data" : "CA030000" },
{ "seq_id" : 1341, "qsl_idx" : 16150, "data" : "0C030000" },
{ "seq_id" : 1342, "qsl_idx" : 7729, "data" : "D6020000" },
{ "seq_id" : 1343, "qsl_idx" : 28282, "data" : "6E000000" },
{ "seq_id" : 1344, "qsl_idx" : 43017, "data" : "6A000000" },
{ "seq_id" : 1345, "qsl_idx" : 17949, "data" : "C0020000" },
{ "seq_id" : 1346, "qsl_idx" : 19742, "data" : "AB000000" },
{ "seq_id" : 1347, "qsl_i

...

ata" : "25020000" },
{ "seq_id" : 49934, "qsl_idx" : 48304, "data" : "7D030000" },
{ "seq_id" : 49935, "qsl_idx" : 22132, "data" : "F9000000" },
{ "seq_id" : 49936, "qsl_idx" : 1129, "data" : "DA030000" },
{ "seq_id" : 49937, "qsl_idx" : 35101, "data" : "30000000" },
{ "seq_id" : 49938, "qsl_idx" : 30049, "data" : "65020000" },
{ "seq_id" : 49939, "qsl_idx" : 21320, "data" : "C8030000" },
{ "seq_id" : 49940, "qsl_idx" : 6471, "data" : "18000000" },
{ "seq_id" : 49941, "qsl_idx" : 13343, "data" : "8E030000" },
{ "seq_id" : 49942, "qsl_idx" : 83, "data" : "3A000000" },
{ "seq_id" : 49943, "qsl_idx" : 43800, "data" : "17000000" },
{ "seq_id" : 49944, "qsl_idx" : 21755, "data" : "B0000000" },
{ "seq_id" : 49945, "qsl_idx" : 29917, "data" : "EB010000" },
{ "seq_id" : 49946, "qsl_idx" : 4992, "data" : "AE010000" },
{ "seq_id" : 49947, "qsl_idx" : 25412, "data" : "79030000" },
{ "seq_id" : 49948, "qsl_idx" : 35689, "data" : "AA020000" },
{ "seq_id" : 49949, "qsl_idx" : 14583, "data" : "54010000" },
{ "seq_id" : 49950, "qsl_idx" : 7324, "data" : "B2020000" },
{ "seq_id" : 49951, "qsl_idx" : 21376, "data" : "CB010000" },
{ "seq_id" : 49952, "qsl_idx" : 2420, "data" : "79030000" },
{ "seq_id" : 49953, "qsl_idx" : 8590, "data" : "42030000" },
{ "seq_id" : 49954, "qsl_idx" : 47447, "data" : "B0030000" },
{ "seq_id" : 49955, "qsl_idx" : 35062, "data" : "4C000000" },
{ "seq_id" : 49956, "qsl_idx" : 46060, "data" : "82010000" },
{ "seq_id" : 49957, "qsl_idx" : 37400, "data" : "FA010000" },
{ "seq_id" : 49958, "qsl_idx" : 31566, "data" : "0E030000" },
{ "seq_id" : 49959, "qsl_idx" : 28650, "data" : "F9020000" },
{ "seq_id" : 49960, "qsl_idx" : 17227, "data" : "1D000000" },
{ "seq_id" : 49961, "qsl_idx" : 29757, "data" : "4D010000" },
{ "seq_id" : 49962, "qsl_idx" : 20765, "data" : "D7000000" },
{ "seq_id" : 49963, "qsl_idx" : 46874, "data" : "67020000" },
{ "seq_id" : 49964, "qsl_idx" : 39568, "data" : "AF000000" },
{ "seq_id" : 49965, "qsl_idx" : 26859, "data" : "D3030000" },
{ "seq_id" : 49966, "qsl_idx" : 21461, "data" : "96030000" },
{ "seq_id" : 49967, "qsl_idx" : 2361, "data" : "96030000" },
{ "seq_id" : 49968, "qsl_idx" : 22151, "data" : "55010000" },
{ "seq_id" : 49969, "qsl_idx" : 42424, "data" : "BB010000" },
{ "seq_id" : 49970, "qsl_idx" : 15063, "data" : "6E010000" },
{ "seq_id" : 49971, "qsl_idx" : 46130, "data" : "3A000000" },
{ "seq_id" : 49972, "qsl_idx" : 31842, "data" : "81030000" },
{ "seq_id" : 49973, "qsl_idx" : 1597, "data" : "0F000000" },
{ "seq_id" : 49974, "qsl_idx" : 21696, "data" : "BA000000" },
{ "seq_id" : 49975, "qsl_idx" : 4090, "data" : "3B010000" },
{ "seq_id" : 49976, "qsl_idx" : 9557, "data" : "4B000000" },
{ "seq_id" : 49977, "qsl_idx" : 9980, "data" : "12000000" },
{ "seq_id" : 49978, "qsl_idx" : 11276, "data" : "B4010000" },
{ "seq_id" : 49979, "qsl_idx" : 36471, "data" : "87010000" },
{ "seq_id" : 49980, "qsl_idx" : 43648, "data" : "5A000000" },
{ "seq_id" : 49981, "qsl_idx" : 31346, "data" : "A4000000" },
{ "seq_id" : 49982, "qsl_idx" : 921, "data" : "BA000000" },
{ "seq_id" : 49983, "qsl_idx" : 45771, "data" : "09030000" },
{ "seq_id" : 49984, "qsl_idx" : 25842, "data" : "D7020000" },
{ "seq_id" : 49985, "qsl_idx" : 45752, "data" : "DB000000" },
{ "seq_id" : 49986, "qsl_idx" : 41966, "data" : "E2020000" },
{ "seq_id" : 49987, "qsl_idx" : 25866, "data" : "3D000000" },
{ "seq_id" : 49988, "qsl_idx" : 26889, "data" : "DA020000" },
{ "seq_id" : 49989, "qsl_idx" : 33762, "data" : "CC000000" },
{ "seq_id" : 49990, "qsl_idx" : 2734, "data" : "9C020000" },
{ "seq_id" : 49991, "qsl_idx" : 19549, "data" : "AC030000" },
{ "seq_id" : 49992, "qsl_idx" : 32396, "data" : "C7020000" },
{ "seq_id" : 49993, "qsl_idx" : 15631, "data" : "B0000000" },
{ "seq_id" : 49994, "qsl_idx" : 3260, "data" : "8C000000" },
{ "seq_id" : 49995, "qsl_idx" : 44383, "data" : "41000000" },
{ "seq_id" : 49996, "qsl_idx" : 43445, "data" : "65030000" },
{ "seq_id" : 49997, "qsl_idx" : 38905, "data" : "6D020000" },
{ "seq_id" : 49998, "qsl_idx" : 45681, "data" : "22020000" },
{ "seq_id" : 49999, "qsl_idx" : 38054, "data" : "B4010000" }
]
