[
{ "seq_id" : 1536, "qsl_idx" : 38706, "data" : "25010000" },
{ "seq_id" : 1537, "qsl_idx" : 39866, "data" : "22020000" },
{ "seq_id" : 1538, "qsl_idx" : 9003, "data" : "AA000000" },
{ "seq_id" : 1539, "qsl_idx" : 22724, "data" : "04010000" },
{ "seq_id" : 1540, "qsl_idx" : 10909, "data" : "A6030000" },
{ "seq_id" : 1541, "qsl_idx" : 28957, "data" : "C6020000" },
{ "seq_id" : 1542, "qsl_idx" : 23916, "data" : "96010000" },
{ "seq_id" : 1543, "qsl_idx" : 41239, "data" : "0A020000" },
{ "seq_id" : 1544, "qsl_idx" : 29950, "data" : "79020000" },
{ "seq_id" : 1545, "qsl_idx" : 31033, "data" : "CA030000" },
{ "seq_id" : 1546, "qsl_idx" : 6946, "data" : "DA000000" },
{ "seq_id" : 1547, "qsl_idx" : 16544, "data" : "AA000000" },
{ "seq_id" : 1548, "qsl_idx" : 46331, "data" : "DA030000" },
{ "seq_id" : 1549, "qsl_idx" : 39391, "data" : "A7030000" },
{ "seq_id" : 1550, "qsl_idx" : 35414, "data" : "8D010000" },
{ "seq_id" : 1551, "qsl_idx" : 41649, "data" : "A9010000" },
{ "seq_id" : 1552, "qsl_idx" : 24501, "data" : "17020000" },
{ "seq_id" : 1553, "qsl_idx" : 13138, "data" : "99030000" },
{ "seq_id" : 1554, "qsl_idx" : 38681, "data" : "01020000" },
{ "seq_id" : 1555, "qsl_idx" : 31051, "data" : "AC010000" },
{ "seq_id" : 1556, "qsl_idx" : 49356, "data" : "1F030000" },
{ "seq_id" : 1557, "qsl_idx" : 7084, "data" : "DC030000" },
{ "seq_id" : 1558, "qsl_idx" : 18090, "data" : "AB020000" },
{ "seq_id" : 1559, "qsl_idx" : 30909, "data" : "C2000000" },
{ "seq_id" : 1560, "qsl_idx" : 36734, "data" : "67020000" },
{ "seq_id" : 1561, "qsl_idx" : 26546, "data" : "0A010000" },
{ "seq_id" : 1562, "qsl_idx" : 30992, "data" : "6C030000" },
{ "seq_id" : 1563, "qsl_idx" : 46887, "data" : "C9020000" },
{ "seq_id" : 1564, "qsl_idx" : 28746, "data" : "9C030000" },
{ "seq_id" : 1565, "qsl_idx" : 25659, "data" : "DD000000" },
{ "seq_id" : 1566, "qsl_idx" : 39437, "data" : "D7020000" },
{ "seq_id" : 1567, "qsl_idx" : 42133, "data" : "39000000" },
{ "seq_id" : 1568, "qsl_idx" : 29478, "data" : "D0010000" },
{ "seq_id" : 1569, "qsl_idx" : 47528, "data" : "7F030000" },
{ "seq_id" : 1570, "qsl_idx" : 11772, "data" : "95010000" },
{ "seq_id" : 1571, "qsl_idx" : 26569, "data" : "7D020000" },
{ "seq_id" : 1572, "qsl_idx" : 28767, "data" : "E3020000" },
{ "seq_id" : 1573, "qsl_idx" : 28072, "data" : "7C000000" },
{ "seq_id" : 1574, "qsl_idx" : 37898, "data" : "67010000" },
{ "seq_id" : 1575, "qsl_idx" : 40427, "data" : "D7010000" },
{ "seq_id" : 1576, "qsl_idx" : 44997, "data" : "65020000" },
{ "seq_id" : 1577, "qsl_idx" : 11222, "data" : "D1020000" },
{ "seq_id" : 1578, "qsl_idx" : 33439, "data" : "DF030000" },
{ "seq_id" : 1579, "qsl_idx" : 6254, "data" : "76030000" },
{ "seq_id" : 1580, "qsl_idx" : 30723, "data" : "14010000" },
{ "seq_id" : 1581, "qsl_idx" : 23536, "data" : "91020000" },
{ "seq_id" : 1582, "qsl_idx" : 2368, "data" : "C8030000" },
{ "seq_id" : 1583, "qsl_idx" : 48994, "data" : "1F000000" },
{ "seq_id" : 1584, "qsl_idx" : 8702, "data" : "BA000000" },
{ "seq_id" : 1585, "qsl_idx" : 37279, "data" : "4B000000" },
{ "seq_id" : 1586, "qsl_idx" : 45965, "data" : "05030000" },
{ "seq_id" : 1587, "qsl_idx" : 980, "data" : "4C010000" },
{ "seq_id" : 1588, "qsl_idx" : 42810, "data" : "3A010000" },
{ "seq_id" : 1589, "qsl_idx" : 40576, "data" : "A0030000" },
{ "seq_id" : 1590, "qsl_idx" : 47548, "data" : "71020000" },
{ "seq_id" : 1591, "qsl_idx" : 21862, "data" : "86030000" },
{ "seq_id" : 1592, "qsl_idx" : 20810, "data" : "6E010000" },
{ "seq_id" : 1593, "qsl_idx" : 3450, "data" : "D1020000" },
{ "seq_id" : 1594, "qsl_idx" : 23179, "data" : "B3000000" },
{ "seq_id" : 1595, "qsl_idx" : 6345, "data" : "35020000" },
{ "seq_id" : 1596, "qsl_idx" : 13547, "data" : "59010000" },
{ "seq_id" : 1597, "qsl_idx" : 22312, "data" : "82000000" },
{ "seq_id" : 1598, "qsl_idx" : 48468, "data" : "DB000000" },
{ "seq_id" : 1599, "qsl_idx" : 17682, "data" : "89010000" },
{ "seq_id" : 1600, "qsl_idx" : 40111, "data" : "5F030000" },
{ "seq_id" : 1601, "qsl_idx" : 1415, "data" : "92010000" },
{ "seq_id" : 1602, "qsl_idx" : 37882, "data" : "8E020000" },
{ "seq_id" : 1603,

...

000000" },
{ "seq_id" : 49598, "qsl_idx" : 8115, "data" : "1A020000" },
{ "seq_id" : 49599, "qsl_idx" : 29226, "data" : "2F010000" },
{ "seq_id" : 49600, "qsl_idx" : 14583, "data" : "54010000" },
{ "seq_id" : 49601, "qsl_idx" : 47341, "data" : "FA000000" },
{ "seq_id" : 49602, "qsl_idx" : 26799, "data" : "27030000" },
{ "seq_id" : 49603, "qsl_idx" : 40464, "data" : "BB010000" },
{ "seq_id" : 49604, "qsl_idx" : 46866, "data" : "E8000000" },
{ "seq_id" : 49605, "qsl_idx" : 8689, "data" : "79030000" },
{ "seq_id" : 49606, "qsl_idx" : 10148, "data" : "AA030000" },
{ "seq_id" : 49607, "qsl_idx" : 20898, "data" : "14020000" },
{ "seq_id" : 49608, "qsl_idx" : 32850, "data" : "70000000" },
{ "seq_id" : 49609, "qsl_idx" : 21312, "data" : "27020000" },
{ "seq_id" : 49610, "qsl_idx" : 32531, "data" : "C1000000" },
{ "seq_id" : 49611, "qsl_idx" : 6426, "data" : "5A010000" },
{ "seq_id" : 49612, "qsl_idx" : 49537, "data" : "6F020000" },
{ "seq_id" : 49613, "qsl_idx" : 7441, "data" : "8D020000" },
{ "seq_id" : 49614, "qsl_idx" : 49172, "data" : "06030000" },
{ "seq_id" : 49615, "qsl_idx" : 18894, "data" : "87000000" },
{ "seq_id" : 49616, "qsl_idx" : 48723, "data" : "7F020000" },
{ "seq_id" : 49617, "qsl_idx" : 2891, "data" : "42020000" },
{ "seq_id" : 49618, "qsl_idx" : 13343, "data" : "8E030000" },
{ "seq_id" : 49619, "qsl_idx" : 14296, "data" : "DA010000" },
{ "seq_id" : 49620, "qsl_idx" : 28630, "data" : "9C000000" },
{ "seq_id" : 49621, "qsl_idx" : 34351, "data" : "B7000000" },
{ "seq_id" : 49622, "qsl_idx" : 45752, "data" : "DB000000" },
{ "seq_id" : 49623, "qsl_idx" : 29917, "data" : "EB010000" },
{ "seq_id" : 49624, "qsl_idx" : 18636, "data" : "7D030000" },
{ "seq_id" : 49625, "qsl_idx" : 43696, "data" : "F4010000" },
{ "seq_id" : 49626, "qsl_idx" : 48046, "data" : "64010000" },
{ "seq_id" : 49627, "qsl_idx" : 34700, "data" : "B8000000" },
{ "seq_id" : 49628, "qsl_idx" : 39535, "data" : "24000000" },
{ "seq_id" : 49629, "qsl_idx" : 34935, "data" : "D2010000" },
{ "seq_id" : 49630, "qsl_idx" : 5677, "data" : "3A020000" },
{ "seq_id" : 49631, "qsl_idx" : 29637, "data" : "87010000" },
{ "seq_id" : 49632, "qsl_idx" : 45995, "data" : "EB020000" },
{ "seq_id" : 49633, "qsl_idx" : 32857, "data" : "B5020000" },
{ "seq_id" : 49634, "qsl_idx" : 11774, "data" : "0C020000" },
{ "seq_id" : 49635, "qsl_idx" : 26427, "data" : "FC010000" },
{ "seq_id" : 49636, "qsl_idx" : 20558, "data" : "8D000000" },
{ "seq_id" : 49637, "qsl_idx" : 14185, "data" : "9F030000" },
{ "seq_id" : 49638, "qsl_idx" : 25385, "data" : "91010000" },
{ "seq_id" : 49639, "qsl_idx" : 13130, "data" : "A4010000" },
{ "seq_id" : 49640, "qsl_idx" : 42138, "data" : "D3020000" },
{ "seq_id" : 49641, "qsl_idx" : 40040, "data" : "5B030000" },
{ "seq_id" : 49642, "qsl_idx" : 13324, "data" : "51020000" },
{ "seq_id" : 49643, "qsl_idx" : 24895, "data" : "EB000000" },
{ "seq_id" : 49644, "qsl_idx" : 33757, "data" : "FA000000" },
{ "seq_id" : 49645, "qsl_idx" : 23679, "data" : "67010000" },
{ "seq_id" : 49646, "qsl_idx" : 38038, "data" : "5F020000" },
{ "seq_id" : 49647, "qsl_idx" : 34035, "data" : "F9000000" },
{ "seq_id" : 49648, "qsl_idx" : 37560, "data" : "D7030000" },
{ "seq_id" : 49649, "qsl_idx" : 41423, "data" : "47020000" },
{ "seq_id" : 49650, "qsl_idx" : 15043, "data" : "D8010000" },
{ "seq_id" : 49651, "qsl_idx" : 10395, "data" : "12030000" },
{ "seq_id" : 49652, "qsl_idx" : 32772, "data" : "41010000" },
{ "seq_id" : 49653, "qsl_idx" : 34446, "data" : "1C020000" },
{ "seq_id" : 49654, "qsl_idx" : 48908, "data" : "26000000" },
{ "seq_id" : 49655, "qsl_idx" : 825, "data" : "51030000" },
{ "seq_id" : 49656, "qsl_idx" : 38167, "data" : "1C010000" },
{ "seq_id" : 49657, "qsl_idx" : 19366, "data" : "81030000" },
{ "seq_id" : 49658, "qsl_idx" : 23220, "data" : "D4010000" },
{ "seq_id" : 49659, "qsl_idx" : 30049, "data" : "65020000" },
{ "seq_id" : 49660, "qsl_idx" : 19631, "data" : "B9020000" },
{ "seq_id" : 49661, "qsl_idx" : 45078, "data" : "C2010000" },
{ "seq_id" : 49662, "qsl_idx" : 33097, "data" : "53000000" },
{ "seq_id" : 49663, "qsl_idx" : 23037, "data" : "E3000000" }
]
