[
  {
    "data": "0000B843",
    "qsl_idx": 6450,
    "seq_id": 0
  },
  {
    "data": "00407344",
    "qsl_idx": 42593,
    "seq_id": 1
  },
  {
    "data": "00402644",
    "qsl_idx": 49654,
    "seq_id": 2
  },
  {
    "data": "0000A343",
    "qsl_idx": 32926,
    "seq_id": 242
  },
  {
    "data": "00001043",
    "qsl_idx": 10135,
    "seq_id": 243
  },
  {
    "data": "0000EF43",
    "qsl_idx": 41518,
    "seq_id": 244
  },
  {
    "data": "00406F44",
    "qsl_idx": 31057,
    "seq_id": 245
  },
  {
    "data": "00006B44",
    "qsl_idx": 27972,
    "seq_id": 246
  },
  {
    "data": "00406E44",
    "qsl_idx": 12581,
    "seq_id": 247
  },
  {
    "data": "0000F843",
    "qsl_idx": 24698,
    "seq_id": 248
  },
  {
    "data": "00006444",
    "qsl_idx": 34431,
    "seq_id": 249
  },
  {
    "data": "00801F44",
    "qsl_idx": 35775,
    "seq_id": 488
  },
  {
    "data": "00006844",
    "qsl_idx": 40576,
    "seq_id": 489
  },
  {
    "data": "00001343",
    "qsl_idx": 28563,
    "seq_id": 490
  },
  {
    "data": "0000FE43",
    "qsl_idx": 23903,
    "seq_id": 491
  },
  {
    "data": "00007C42",
    "qsl_idx": 46943,
    "seq_id": 492
  },
  {
    "data": "00401C44",
    "qsl_idx": 14118,
    "seq_id": 493
  },
  {
    "data": "00C01A44",
    "qsl_idx": 44446,
    "seq_id": 494
  },
  {
    "data": "00809243",
    "qsl_idx": 9132,
    "seq_id": 495
  },
  {
    "data": "00002D44",
    "qsl_idx": 30816,
    "seq_id": 11
  },
  {
    "data": "00808243",
    "qsl_idx": 28869,
    "seq_id": 12
  },
  {
    "data": "00002F43",
    "qsl_idx": 33125,
    "seq_id": 13
  },
  {
    "data": "0000AE43",
    "qsl_idx": 23651,
    "seq_id": 14
  },
  {
    "data": "00006543",
    "qsl_idx": 30830,
    "seq_id": 15
  },
  {
    "data": "00406D44",
    "qsl_idx": 32410,
    "seq_id": 16
  },
  {
    "data": "0000D343",
    "qsl_idx": 37607,
    "seq_id": 17
  },
  {
    "data": "00C01444",
    "qsl_idx": 46733,
    "seq_id": 18
  },
  {
    "data": "00002443",
    "qsl_idx": 45886,
    "seq_id": 258
  },
  {
    "data": "00402844",
    "qsl_idx": 19862,
    "seq_id": 259
  },
  {
    "data": "00006943",
    "qsl_idx": 7673,
    "seq_id": 260
  },
  {
    "data": "00001042",
    "qsl_idx": 24493,
    "seq_id": 261
  },
  {
    "data": "00005444",
    "qsl_idx": 35510,
    "seq_id": 262
  },
  {
    "data": "00007C42",
    "qsl_idx": 36340,
    "seq_id": 263
  },
  {
    "data": "0080EB43",
    "qsl_idx": 1445,
    "seq_id": 264
  },
  {
    "data": "00009A43",
    "qsl_idx": 36433,
    "seq_id": 265
  },
  {
    "data": "0000FF43",
    "qsl_idx": 3366,
    "seq_id": 504
  },
  {
    "data": "00401544",
    "qsl_idx": 37224,
    "seq_id": 505
  },
  {
    "data": "0080D643",
    "qsl_idx": 26505,
    "seq_id": 506
  },
  {
    "data": "00C01C44",
    "qsl_idx": 3923,
    "seq_id": 507
  },
  {
    "data": "00403844",
    "qsl_idx": 1969,
    "seq_id": 508
  },
  {
    "data": "00008943",
    "qsl_idx": 7525,
    "seq_id": 509
  },
  {
    "data": "0080C643",
    "qsl_idx": 1192,
    "seq_id": 510
  },
  {
    "data": "00C04C44",
    "qsl_idx": 1357,
    "seq_id": 511
  },
  {
    "data": "0000EA43",
    "qsl_idx": 46452,
    "seq_id": 3
  },
  {
    "data": "00407544",
    "qsl_idx": 24078,
    "seq_id": 4
  },
  {
    "data": "00005042",
    "qsl_idx": 4268,
    "seq_id": 5
  },
  {
    "data": "0080E743",
    "qsl_idx": 16922,
    "seq_id": 6
  },
  {
    "data": "0000CC42",
    "qsl_idx": 26262,
    "seq_id": 7
  },
  {
    "data": "0080C943",
    "qsl_idx": 11404,
    "seq_id": 8
  },
  {
    "data": "00405F44",
    "qsl_idx": 43754,
    "seq_id": 9
  },
  {
    "data": "00402E44",
    "qsl_idx": 34906,
    "seq_id": 10
  },
  {
    "data": "00007D43",
    "qsl_idx": 39497,
    "seq_id": 250
  },
  {
    "data": "00806844",
    "qsl_idx": 31762,
    "seq_id": 251
  },
  {
    "data": "00C04144",
    "qsl_idx": 20029,
    "seq_id": 252
  },
  {
    "data": "00005743",
    "qsl_idx": 18991,
    "seq_id": 253
  },
  {
    "data": "0080E143",
    "qsl_idx": 15943,
    "seq_id": 254
  },
  {
    "data": "00808F43",
    "qsl_idx": 449

...

00005C44",
    "qsl_idx": 46548,
    "seq_id": 49440
  },
  {
    "data": "00009943",
    "qsl_idx": 11898,
    "seq_id": 49441
  },
  {
    "data": "00003543",
    "qsl_idx": 33214,
    "seq_id": 49442
  },
  {
    "data": "00404644",
    "qsl_idx": 30669,
    "seq_id": 49443
  },
  {
    "data": "00000D43",
    "qsl_idx": 19388,
    "seq_id": 49444
  },
  {
    "data": "0000B743",
    "qsl_idx": 40007,
    "seq_id": 49445
  },
  {
    "data": "00004144",
    "qsl_idx": 48964,
    "seq_id": 49446
  },
  {
    "data": "00802D44",
    "qsl_idx": 30002,
    "seq_id": 49683
  },
  {
    "data": "00000344",
    "qsl_idx": 9206,
    "seq_id": 49684
  },
  {
    "data": "00406144",
    "qsl_idx": 34448,
    "seq_id": 49685
  },
  {
    "data": "00804044",
    "qsl_idx": 39727,
    "seq_id": 49686
  },
  {
    "data": "00801344",
    "qsl_idx": 5408,
    "seq_id": 49687
  },
  {
    "data": "00002E44",
    "qsl_idx": 39860,
    "seq_id": 49688
  },
  {
    "data": "0080ED43",
    "qsl_idx": 43163,
    "seq_id": 49689
  },
  {
    "data": "00004F44",
    "qsl_idx": 8445,
    "seq_id": 49690
  },
  {
    "data": "00003543",
    "qsl_idx": 7891,
    "seq_id": 49931
  },
  {
    "data": "0080B143",
    "qsl_idx": 9718,
    "seq_id": 49932
  },
  {
    "data": "00809F43",
    "qsl_idx": 44602,
    "seq_id": 49933
  },
  {
    "data": "00805A44",
    "qsl_idx": 5479,
    "seq_id": 49934
  },
  {
    "data": "00808643",
    "qsl_idx": 11462,
    "seq_id": 49935
  },
  {
    "data": "0000B443",
    "qsl_idx": 11215,
    "seq_id": 49936
  },
  {
    "data": "00C01344",
    "qsl_idx": 42558,
    "seq_id": 49937
  },
  {
    "data": "00404244",
    "qsl_idx": 15511,
    "seq_id": 49938
  },
  {
    "data": "0000C743",
    "qsl_idx": 41191,
    "seq_id": 49203
  },
  {
    "data": "00007544",
    "qsl_idx": 27614,
    "seq_id": 49204
  },
  {
    "data": "00404644",
    "qsl_idx": 11123,
    "seq_id": 49205
  },
  {
    "data": "00806744",
    "qsl_idx": 21893,
    "seq_id": 49206
  },
  {
    "data": "00809E43",
    "qsl_idx": 28802,
    "seq_id": 49207
  },
  {
    "data": "00404B44",
    "qsl_idx": 3368,
    "seq_id": 49208
  },
  {
    "data": "00800844",
    "qsl_idx": 1835,
    "seq_id": 49209
  },
  {
    "data": "0000E041",
    "qsl_idx": 33766,
    "seq_id": 49210
  },
  {
    "data": "00006344",
    "qsl_idx": 49061,
    "seq_id": 49455
  },
  {
    "data": "00C01344",
    "qsl_idx": 45091,
    "seq_id": 49456
  },
  {
    "data": "00001643",
    "qsl_idx": 23080,
    "seq_id": 49457
  },
  {
    "data": "00004C43",
    "qsl_idx": 37852,
    "seq_id": 49458
  },
  {
    "data": "00805044",
    "qsl_idx": 3552,
    "seq_id": 49459
  },
  {
    "data": "00000144",
    "qsl_idx": 17997,
    "seq_id": 49460
  },
  {
    "data": "0000E442",
    "qsl_idx": 29474,
    "seq_id": 49461
  },
  {
    "data": "00006442",
    "qsl_idx": 10139,
    "seq_id": 49462
  },
  {
    "data": "00805244",
    "qsl_idx": 12149,
    "seq_id": 49699
  },
  {
    "data": "0080EC43",
    "qsl_idx": 1944,
    "seq_id": 49700
  },
  {
    "data": "00C07244",
    "qsl_idx": 24380,
    "seq_id": 49701
  },
  {
    "data": "00C05644",
    "qsl_idx": 40040,
    "seq_id": 49702
  },
  {
    "data": "00001544",
    "qsl_idx": 31054,
    "seq_id": 49703
  },
  {
    "data": "0000F243",
    "qsl_idx": 42035,
    "seq_id": 49704
  },
  {
    "data": "0000CE43",
    "qsl_idx": 22652,
    "seq_id": 49705
  },
  {
    "data": "00001D43",
    "qsl_idx": 36011,
    "seq_id": 49706
  },
  {
    "data": "00001842",
    "qsl_idx": 44320,
    "seq_id": 49947
  },
  {
    "data": "00800244",
    "qsl_idx": 4047,
    "seq_id": 49948
  },
  {
    "data": "00403B44",
    "qsl_idx": 36793,
    "seq_id": 49949
  },
  {
    "data": "0000E743",
    "qsl_idx": 24492,
    "seq_id": 49950
  },
  {
    "data": "00003143",
    "qsl_idx": 24830,
    "seq_id": 49951
  },
  {
    "data": "0000B943",
    "qsl_idx": 16598,
    "seq_id": 49952
  },
  {
    "data": "00000243",
    "qsl_idx": 41082,
    "seq_id": 49953
  },
  {
    "data": "00003B44",
    "qsl_idx": 5665,
    "seq_id": 49954
  }
]